[
{"name": "\n\nAOK - Die Gesundheitskasse für Niedersachsen   \n\n", "link": "http://www.aok.de/niedersachsen", "fee": "\n1,50 %\n", "location": "\nNiedersachsen\n"},
{"name": "\n\nAOK - Die Gesundheitskasse in Hessen   \n\n", "link": "http://www.aok.de/hessen", "fee": "\n1,60 %\n", "location": "\nHessen\n"},
{"name": "\n\nAOK Baden-Württemberg   \n\n", "link": "http://www.aok.de/baden-wuerttemberg/index.php", "fee": "\n1,60 %\n", "location": "\nBaden-Württemberg\n"},
{"name": "\n\nAOK Bayern - Die Gesundheitskasse   \n\n", "link": "http://www.aok.de/bayern", "fee": "\n1,58 %\n", "location": "\nBayern\n"},
{"name": "\n\nAOK Bremen / Bremerhaven   \n\n", "link": "http://www.aok.de/bremen", "fee": "\n1,60 %\n", "location": "\nBremen\n"},
{"name": "\n\nAOK Nordost - Die Gesundheitskasse   \n\n", "link": "http://www.aok.de/nordost/", "fee": "\n1,90 %\n", "location": "\nBerlin, Brandenburg, Mecklenburg-Vorpommern\n"},
{"name": "\n\nAOK NordWest - Die Gesundheitskasse   \n\n", "link": "http://www.aok.de/nordwest", "fee": "\n1,89 %\n", "location": "\nNordrhein-Westfalen, Schleswig-Holstein\n"},
{"name": "\n\nAOK PLUS - Die Gesundheitskasse für Sachsen und   Thüringen  \n\n", "link": "http://www.aok.de/aokplus", "fee": "\n1,50 %\n", "location": "\nSachsen, Thüringen\n"},
{"name": "\n\nAOK Rheinland/Hamburg - Die Gesundheitskasse   \n\n", "link": "http://www.aok.de/rheinland-hamburg", "fee": "\n1,80 %\n", "location": "\nHamburg, Nordrhein-Westfalen\n"},
{"name": "\n\nAOK Rheinland-Pfalz/Saarland-Die Gesundheitskasse   \n\n", "link": "http://www.aok.de/rheinland-pfalz-saarland/", "fee": "\n1,80 %\n", "location": "\nRheinland-Pfalz, Saarland\n"},
{"name": "\n\nAOK Sachsen-Anhalt - Die Gesundheitskasse   \n\n", "link": "http://www.aok.de/sachsen-anhalt", "fee": "\n1,00 %\n", "location": "\nSachsen-Anhalt\n"},
{"name": "\n\nAudi BKK   \n\n", "link": "http://www.Audibkk.de", "fee": "\n1,25 %\n", "location": "\nbundesweit\n"},
{"name": "\n\nBAHN-BKK   \n\n", "link": "http://www.bahn-bkk.de", "fee": "\n1,70 %\n", "location": "\nbundesweit\n"},
{"name": "\n\nBARMER   \n\n", "link": "http://www.barmer.de", "fee": "\n1,50 %\n", "location": "\nbundesweit\n"},
{"name": "\n\nBERGISCHE KRANKENKASSE   \n\n", "link": "http://www.bergische-krankenkasse.de", "fee": "\n1,60 %\n", "location": "\nHamburg, Hessen, Nordrhein-Westfalen\n"},
{"name": "\n\nBertelsmann BKK   \n\n", "link": "http://www.bertelsmann-bkk.de", "fee": "\n1,40 %\n", "location": "\nBaden-Württemberg, Bayern, Berlin, Hamburg, Niedersachsen, Nordrhein-Westfalen, Sachsen, Thüringen\n"},
{"name": "\n\nBetriebskrankenkasse Mobil   \n\n", "link": "http://www.mobil-krankenkasse.de", "fee": "\n1,49 %\n", "location": "\nbundesweit\n"},
{"name": "\n\nBetriebskrankenkasse PricewaterhouseCoopers   \n\n", "link": "http://www.bkk-pwc.de", "fee": "\n1,48 %\n", "location": "\nbetriebs­be­zogen (nur für Mitar­beitende wählbar)\n"},
{"name": "\n\nBIG direkt gesund   \n\n", "link": "http://www.big-direkt.de", "fee": "\n1,45 %\n", "location": "\nbundesweit\n"},
{"name": "\n\nBKK Akzo Nobel Bayern   \n\n", "link": "http://www.bkk-akzo.de", "fee": "\n1,55 %\n", "location": "\nBayern\n"},
{"name": "\n\nBKK B. Braun Aesculap   \n\n", "link": "http://www.bkk-bba.de", "fee": "\n1,75 %\n", "location": "\nbetriebs­be­zogen (nur für Mitar­beitende wählbar)\n"},
{"name": "\n\nBKK BPW Bergische Achsen KG    \n\n", "link": "http://www.bkk-bpw.de", "fee": "\n1,80 %\n", "location": "\nbetriebs­be­zogen (nur für Mitar­beitende wählbar)\n"},
{"name": "\n\nBKK Deutsche Bank AG   \n\n", "link": "http://www.bkk-deutsche-bank.de", "fee": "\n1,60 %\n", "location": "\nbetriebs­be­zogen (nur für Mitar­beitende wählbar)\n"},
{"name": "\n\nBKK Diakonie   \n\n", "link": "http://www.bkk-diakonie.de", "fee": "\n1,60 %\n", "location": "\nBaden-Württemberg, Bayern, Berlin, Brandenburg, Bremen, Hamburg, Hessen, Mecklenburg-Vorpommern, Niedersachsen, Nordrhein-Westfalen, Rheinland-Pfalz, Sachsen, Sachsen-Anhalt, Schleswig-Holstein\n"},
{"name": "\n\nBKK EUREGIO   \n\n", "link": "http://www.bkk-euregio.de", "fee": "\n0,84 %\n", "location": "\nHamburg, Nordrhein-Westfalen\n"},
{"name": "\n\nBKK EVM   \n\n", "link": "http://www.bkk-evm.de", "fee": "\n0,90 %\n", "location": "\nbetriebs­be­zogen (nur für Mitar­beitende wählbar)\n"},
{"name": "\n\nBKK EWE   \n\n", "link": "http://www.bkk-ewe.de", "fee": "\n0,90 %\n", "location": "\nbetriebs­be­zogen (nur für Mitar­beitende wählbar)\n"},
{"name": "\n\nBKK exklusiv   \n\n", "link": "http://www.bkkexklusiv.de", "fee": "\n1,99 %\n", "location": "\nBremen, Mecklenburg-Vorpommern, Niedersachsen, Nordrhein-Westfalen, Sachsen-Anhalt, Schleswig-Holstein\n"},
{"name": "\n\nBKK Faber-Castell & Partner   \n\n", "link": "http://www.bkk-faber-castell.de", "fee": "\n1,35 %\n", "location": "\nBayern\n"},
{"name": "\n\nBKK firmus   \n\n", "link": "http://www.bkk-firmus.de", "fee": "\n0,90 %\n", "location": "\nbundesweit\n"},
{"name": "\n\nBKK Freudenberg   \n\n", "link": "http://www.bkk-freudenberg.de", "fee": "\n1,50 %\n", "location": "\nBaden-Württemberg, Bayern, Berlin, Hessen, Niedersachsen, Nordrhein-Westfalen, Rheinland-Pfalz, Sachsen\n"},
{"name": "\n\nBKK GILDEMEISTER SEIDENSTICKER   \n\n", "link": "http://www.bkkgilsei.de", "fee": "\n0,90 %\n", "location": "\nbundesweit\n"},
{"name": "\n\nBKK Groz-Beckert   \n\n", "link": "http://www.bkk-gb.de", "fee": "\n0,40 %\n", "location": "\nbetriebs­be­zogen (nur für Mitar­beitende wählbar)\n"},
{"name": "\n\nBKK Herkules   \n\n", "link": "http://www.bkk-herkules.de/", "fee": "\n1,09 %\n", "location": "\nBayern, Hessen, Niedersachsen\n"},
{"name": "\n\nBKK Linde   \n\n", "link": "http://www.bkk-linde.de", "fee": "\n1,50 %\n", "location": "\nbundesweit\n"},
{"name": "\n\nBKK MAHLE   \n\n", "link": "http://www.bkk-mahle.de", "fee": "\n1,50 %\n", "location": "\nbetriebs­be­zogen (nur für Mitar­beitende wählbar)\n"},
{"name": "\n\nbkk melitta hmr   \n\n", "link": "http://www.bkk-melitta-hmr.de/", "fee": "\n1,40 %\n", "location": "\nBaden-Württemberg, Bayern, Brandenburg, Bremen, Hessen, Niedersachsen, Nordrhein-Westfalen, Sachsen, Sachsen-Anhalt, Schleswig-Holstein\n"},
{"name": "\n\nBKK Miele   \n\n", "link": "http://www.bkk-miele.de", "fee": "\n1,40 %\n", "location": "\nbetriebs­be­zogen (nur für Mitar­beitende wählbar)\n"},
{"name": "\n\nBKK MTU    \n\n", "link": "http://www.bkk-mtu.de", "fee": "\n1,60 %\n", "location": "\nbetriebs­be­zogen (nur für Mitar­beitende wählbar)\n"},
{"name": "\n\nBKK PFAFF    \n\n", "link": "http://www.bkk-pfaff.de", "fee": "\n0,80 %\n", "location": "\nRheinland-Pfalz\n"},
{"name": "\n\nBKK Pfalz   \n\n", "link": "http://www.bkkpfalz.de", "fee": "\n1,55 %\n", "location": "\nbundesweit\n"},
{"name": "\n\nBKK ProVita   \n\n", "link": "http://www.bkk-provita.de/", "fee": "\n1,49 %\n", "location": "\nbundesweit\n"},
{"name": "\n\nBKK Public   \n\n", "link": "http://www.bkk-public.de", "fee": "\n1,50 %\n", "location": "\nHamburg, Niedersachsen, Nordrhein-Westfalen\n"},
{"name": "\n\nBKK Rieker.RICOSTA.Weisser   \n\n", "link": "http://www.bkk-rrw.de", "fee": "\n2,00 %\n", "location": "\nbetriebs­be­zogen (nur für Mitar­beitende wählbar)\n"},
{"name": "\n\nBKK Salzgitter   \n\n", "link": "http://www.bkk-salzgitter.de", "fee": "\n1,60 %\n", "location": "\nbetriebs­be­zogen (nur für Mitar­beitende wählbar)\n"},
{"name": "\n\nBKK Scheufelen   \n\n", "link": "http://www.bkk-scheufelen.de", "fee": "\n1,40 %\n", "location": "\nBaden-Württemberg\n"},
{"name": "\n\nBKK Schwarzwald-Baar-Heuberg   \n\n", "link": "http://www.bkk-sbh.de", "fee": "\n0,98 %\n", "location": "\nBaden-Württemberg\n"},
{"name": "\n\nBKK Technoform   \n\n", "link": "http://www.bkk-technoform.de", "fee": "\n1,50 %\n", "location": "\nBaden-Württemberg, Bayern, Niedersachsen, Rheinland-Pfalz\n"},
{"name": "\n\nBKK Textilgruppe Hof   \n\n", "link": "http://www.bkk-textilgruppe-hof.de", "fee": "\n0,90 %\n", "location": "\nBayern\n"},
{"name": "\n\nBKK VDN   \n\n", "link": "http://www.bkk-vdn.de", "fee": "\n1,50 %\n", "location": "\nHamburg, Nordrhein-Westfalen, Sachsen\n"},
{"name": "\n\nBKK VerbundPlus   \n\n", "link": "http://www.bkk-verbundplus.de", "fee": "\n1,35 %\n", "location": "\nbundesweit\n"},
{"name": "\n\nBKK Verkehrsbau Union (BKK VBU)    \n\n", "link": "http://www.meine-krankenkasse.de", "fee": "\n1,80 %\n", "location": "\nbundesweit\n"},
{"name": "\n\nBKK Voralb HELLER*INDEX*LEUZE   \n\n", "link": "http://www.bkk-voralb.de", "fee": "\n0,50 %\n", "location": "\nbetriebs­be­zogen (nur für Mitar­beitende wählbar)\n"},
{"name": "\n\nBKK Werra-Meissner   \n\n", "link": "http://www.bkk-werra-meissner.de", "fee": "\n1,80 %\n", "location": "\nBayern, Hessen\n"},
{"name": "\n\nBKK Wirtschaft & Finanzen   \n\n", "link": "http://www.bkk-wf.de/", "fee": "\n1,69 %\n", "location": "\nBaden-Württemberg, Bayern, Berlin, Brandenburg, Bremen, Hamburg, Hessen, Niedersachsen, Nordrhein-Westfalen, Rheinland-Pfalz, Saarland, Sachsen\n"},
{"name": "\n\nBKK Würth   \n\n", "link": "http://www.bkk-wuerth.de", "fee": "\n0,98 %\n", "location": "\nbetriebs­be­zogen (nur für Mitar­beitende wählbar)\n"},
{"name": "\n\nBKK ZF & Partner   \n\n", "link": "http://www.bkk-zf-partner.de", "fee": "\n1,45 %\n", "location": "\nBaden-Württemberg, Bayern, Berlin, Brandenburg, Bremen, Hamburg, Hessen, Niedersachsen, Nordrhein-Westfalen, Rheinland-Pfalz, Saarland, Sachsen, Sachsen-Anhalt, Thüringen\n"},
{"name": "\n\nBKK_DürkoppAdler   \n\n", "link": "http://www.bkk-da.de", "fee": "\n1,29 %\n", "location": "\nNordrhein-Westfalen\n"},
{"name": "\n\nBKK24   \n\n", "link": "http://www.bkk24.de", "fee": "\n1,79 %\n", "location": "\nbundesweit\n"},
{"name": "\n\nBMW BKK   \n\n", "link": "http://www.bmwbkk.de", "fee": "\n0,30 %\n", "location": "\nbetriebs­be­zogen (nur für Mitar­beitende wählbar)\n"},
{"name": "\n\nBosch BKK   \n\n", "link": "http://www.bosch-bkk.de", "fee": "\n1,50 %\n", "location": "\nBaden-Württemberg, Bayern, Berlin, Brandenburg, Hamburg, Hessen, Mecklenburg-Vorpommern, Niedersachsen, Nordrhein-Westfalen, Rheinland-Pfalz, Saarland, Sachsen, Sachsen-Anhalt, Thüringen\n"},
{"name": "\n\nContinentale Betriebskrankenkasse   \n\n", "link": "http://www.continentale-bkk.de", "fee": "\n1,40 %\n", "location": "\nbundesweit\n"},
{"name": "\n\nDAK-Gesundheit   \n\n", "link": "http://www.dak.de", "fee": "\n1,70 %\n", "location": "\nbundesweit\n"},
{"name": "\n\nDebeka BKK   \n\n", "link": "http://www.debeka-bkk.de", "fee": "\n1,69 %\n", "location": "\nbundesweit\n"},
{"name": "\n\nenergie-Betriebskrankenkasse   \n\n", "link": "http://www.energie-bkk.de", "fee": "\n1,59 %\n", "location": "\nbundesweit\n"},
{"name": "\n\nErnst & Young BKK   \n\n", "link": "http://www.ey-bkk.de", "fee": "\n1,54 %\n", "location": "\nbetriebs­be­zogen (nur für Mitar­beitende wählbar)\n"},
{"name": "\n\nHandelskrankenkasse (hkk)    \n\n", "link": "http://www.hkk.de", "fee": "\n0,98 %\n", "location": "\nbundesweit\n"},
{"name": "\n\nHeimat Krankenkasse   \n\n", "link": "http://www.heimat-krankenkasse.de", "fee": "\n1,30 %\n", "location": "\nbundesweit\n"},
{"name": "\n\nHEK - Hanseatische Krankenkasse   \n\n", "link": "http://www.hek.de", "fee": "\n1,30 %\n", "location": "\nbundesweit\n"},
{"name": "\n\nIKK - Die Innovationskasse (IK)   \n\n", "link": "http://www.die-ik.de/", "fee": "\n1,60 %\n", "location": "\nbundesweit\n"},
{"name": "\n\nIKK Brandenburg und Berlin   \n\n", "link": "http://www.ikkbb.de", "fee": "\n1,77 %\n", "location": "\nBerlin, Brandenburg\n"},
{"name": "\n\nIKK classic   \n\n", "link": "http://www.ikk-classic.de", "fee": "\n1,60 %\n", "location": "\nbundesweit\n"},
{"name": "\n\nIKK gesund plus   \n\n", "link": "http://www.ikk-gesundplus.de", "fee": "\n1,10 %\n", "location": "\nbundesweit\n"},
{"name": "\n\nIKK Südwest   \n\n", "link": "http://www.ikk-suedwest.de", "fee": "\n1,65 %\n", "location": "\nHessen, Rheinland-Pfalz, Saarland\n"},
{"name": "\n\nKARL MAYER BKK   \n\n", "link": "http://www.karlmayer-bkk.de", "fee": "\n1,90 %\n", "location": "\nbetriebs­be­zogen (nur für Mitar­beitende wählbar)\n"},
{"name": "\n\nKaufmännische Krankenkasse - KKH   \n\n", "link": "http://www.kkh.de", "fee": "\n1,50 %\n", "location": "\nbundesweit\n"},
{"name": "\n\nKNAPPSCHAFT   \n\n", "link": "http://www.knappschaft.de", "fee": "\n1,60 %\n", "location": "\nbundesweit\n"},
{"name": "\n\nKoenig & Bauer BKK   \n\n", "link": "http://www.koenig-bauer-bkk.de", "fee": "\n1,44 %\n", "location": "\nbetriebs­be­zogen (nur für Mitar­beitende wählbar)\n"},
{"name": "\n\nKrones BKK   \n\n", "link": "http://www.bkk-krones.de", "fee": "\n0,90 %\n", "location": "\nbetriebs­be­zogen (nur für Mitar­beitende wählbar)\n"},
{"name": "\n\nMercedes-Benz BKK   \n\n", "link": "http://www.mercedes-benz-bkk.com//", "fee": "\n1,30 %\n", "location": "\nbetriebs­be­zogen (nur für Mitar­beitende wählbar)\n"},
{"name": "\n\nMerck BKK    \n\n", "link": "http://www.merck-bkk.de", "fee": "\n1,40 %\n", "location": "\nbetriebs­be­zogen (nur für Mitar­beitende wählbar)\n"},
{"name": "\n\nmhplus Betriebskrankenkasse   \n\n", "link": "http://www.mhplus.de", "fee": "\n1,58 %\n", "location": "\nBaden-Württemberg, Bayern, Berlin, Hamburg, Hessen, Mecklenburg-Vorpommern, Niedersachsen, Nordrhein-Westfalen, Rheinland-Pfalz, Sachsen, Sachsen-Anhalt, Schleswig-Holstein, Thüringen\n"},
{"name": "\n\nNovitas BKK   \n\n", "link": "http://www.novitas-bkk.de", "fee": "\n1,54 %\n", "location": "\nbundesweit\n"},
{"name": "\n\nPronova BKK   \n\n", "link": "http://www.pronovabkk.de", "fee": "\n1,70 %\n", "location": "\nbundesweit\n"},
{"name": "\n\nR+V Betriebskrankenkasse   \n\n", "link": "http://www.ruv-bkk.de", "fee": "\n1,40 %\n", "location": "\nbundesweit\n"},
{"name": "\n\nSalus BKK   \n\n", "link": "http://www.salus-bkk.de", "fee": "\n1,59 %\n", "location": "\nbundesweit\n"},
{"name": "\n\nSECURVITA BKK   \n\n", "link": "http://www.securvita.de", "fee": "\n1,60 %\n", "location": "\nBaden-Württemberg, Bayern, Berlin, Brandenburg, Hamburg, Hessen, Mecklenburg-Vorpommern, Niedersachsen, Nordrhein-Westfalen, Rheinland-Pfalz, Sachsen, Sachsen-Anhalt, Schleswig-Holstein, Thüringen\n"},
{"name": "\n\nSiemens-Betriebskrankenkasse (SBK)   \n\n", "link": "http://www.sbk.org", "fee": "\n1,50 %\n", "location": "\nbundesweit\n"},
{"name": "\n\nSKD BKK   \n\n", "link": "http://www.skd-bkk.de", "fee": "\n1,15 %\n", "location": "\nBaden-Württemberg, Bayern, Berlin, Bremen, Hamburg, Hessen, Niedersachsen, Nordrhein-Westfalen, Saarland, Sachsen, Schleswig-Holstein\n"},
{"name": "\n\nSozialversicherung für Landwirtschaft, Forsten und Gartenbau (SVLFG)  \n\n", "link": "http://www.svlfg.de", "fee": "\nwird nicht erhoben\n", "location": "\nbranchenbezogen\n"},
{"name": "\n\nSüdzucker BKK   \n\n", "link": "http://www.suedzucker-bkk.de", "fee": "\n1,10 %\n", "location": "\nbetriebs­be­zogen (nur für Mitar­beitende wählbar)\n"},
{"name": "\n\nTechniker Krankenkasse   \n\n", "link": "http://www.tk.de", "fee": "\n1,20 %\n", "location": "\nbundesweit\n"},
{"name": "\n\nTUI BKK   \n\n", "link": "http://www.tui-bkk.de/", "fee": "\n1,50 %\n", "location": "\nbundesweit\n"},
{"name": "\n\nVIACTIV Krankenkasse   \n\n", "link": "http://www.viactiv.de", "fee": "\n1,60 %\n", "location": "\nbundesweit\n"},
{"name": "\n\nvivida bkk   \n\n", "link": "http://www.vividabkk.de/", "fee": "\n1,40 %\n", "location": "\nbundesweit\n"},
{"name": "\n\nWMF Betriebskrankenkasse   \n\n", "link": "http://www.wmf-bkk.de", "fee": "\n1,60 %\n", "location": "\nbundesweit\n"}
]